airflow_models/__init__.py
airflow_models/assignment.py
airflow_models/company.py
airflow_models/concilia_erp_sat_config.py
airflow_models/conciliation_report.py
airflow_models/customer.py
airflow_models/data_erp_config.py
airflow_models/datasource_config.py
airflow_models/datasource_upload.py
airflow_models/excel_data_type.py
airflow_models/project.py
airflow_models/project_type.py
airflow_models/report_config.py
airflow_models/report_type.py
daos/__init__.py
daos/assignment_dao.py
daos/company_dao.py
daos/concilia_erp_sat_config_dao.py
daos/conciliation_report_dao.py
daos/customer_dao.py
daos/data_erp_config_dao.py
daos/datasource_config_dao.py
daos/datasource_upload_dao.py
daos/excel_data_type_dao.py
daos/project_dao.py
daos/project_type_dao.py
daos/report_type_dao.py
mongo/__init__.py
mongo/core/__init__.py
mongo/core/base_mongo_dao.py
mongo/core/base_mongo_model.py
mongo/core/mongo_collection.py
mongo/core/mongo_connection.py
mongo/core/objectid.py
mongo/pydantic_types/__init__.py
mongo/pydantic_types/date.py
mongo/pydantic_types/rfc_str.py
mongo/pydantic_types/uuid_str.py
s3/__init__.py
s3/files/__init__.py
s3/files/aws_wrapper.py
s3/files/bucket_manager.py
s3/files/file_manager.py
tools/__init__.py
tools/env.py
tools/datasources/__init__.py
tools/datasources/abc_datasource.py
tools/datasources/csv_datasource.py
tools/datasources/excel_datasource.py
conciliation_models-0.1.1.dist-info/LICENSE.txt
conciliation_models-0.1.1.dist-info/METADATA
conciliation_models-0.1.1.dist-info/WHEEL
conciliation_models-0.1.1.dist-info/top_level.txt
conciliation_models-0.1.1.dist-info/RECORD
